eson/__init__.py
eson/config.py
eson/decoder.py
eson/encoder.py
eson/extensions/__init__.py
eson/extensions/date.py
eson/extensions/datetime.py
eson-0.0.3.dist-info/METADATA
eson-0.0.3.dist-info/WHEEL
eson-0.0.3.dist-info/top_level.txt
eson-0.0.3.dist-info/RECORD
