Metadata-Version: 2.1
Name: eson
Version: 0.0.3
Summary: Extendable JSON to support different formats of data across languages. By default supports date and datetime objects
Home-page: https://github.com/Billcountry/eson
Author: Billcountry
Author-email: me@billcountry.tech
License: UNKNOWN
Platform: UNKNOWN
Classifier: Programming Language :: Python :: 3
Classifier: License :: OSI Approved :: MIT License
Classifier: Operating System :: OS Independent
